odoo/addons/sm_carsharing_structure_sommobilitat/__init__.py
odoo/addons/sm_carsharing_structure_sommobilitat/__manifest__.py
odoo/addons/sm_carsharing_structure_sommobilitat/data/fleet_vehicle_battery_maximum_charges.xml
odoo/addons/sm_carsharing_structure_sommobilitat/data/fleet_vehicle_battery_sizes.xml
odoo/addons/sm_carsharing_structure_sommobilitat/data/fleet_vehicle_state.xml
odoo/addons/sm_carsharing_structure_sommobilitat/models/__init__.py
odoo/addons/sm_carsharing_structure_sommobilitat/models/fleet_vehicle_battery_maximum_charge.py
odoo/addons/sm_carsharing_structure_sommobilitat/models/fleet_vehicle_battery_size.py
odoo/addons/sm_carsharing_structure_sommobilitat/models/fleet_vehicle_state.py
odoo/addons/sm_carsharing_structure_sommobilitat/models/models_cs_car.py
odoo/addons/sm_carsharing_structure_sommobilitat/models/res_company.py
odoo/addons/sm_carsharing_structure_sommobilitat/models/res_config_settings.py
odoo/addons/sm_carsharing_structure_sommobilitat/security/ir.model.access.csv
odoo/addons/sm_carsharing_structure_sommobilitat/views/fleet_vehicle_battery_maximum_charge.xml
odoo/addons/sm_carsharing_structure_sommobilitat/views/fleet_vehicle_battery_size_view.xml
odoo/addons/sm_carsharing_structure_sommobilitat/views/fleet_vehicle_state_view.xml
odoo/addons/sm_carsharing_structure_sommobilitat/views/views_cs_car.xml
odoo/addons/sm_carsharing_structure_sommobilitat/views/views_res_config_settings.xml
odoo12_addon_sm_carsharing_structure_sommobilitat-12.0.0.0.11.dist-info/METADATA
odoo12_addon_sm_carsharing_structure_sommobilitat-12.0.0.0.11.dist-info/WHEEL
odoo12_addon_sm_carsharing_structure_sommobilitat-12.0.0.0.11.dist-info/top_level.txt
odoo12_addon_sm_carsharing_structure_sommobilitat-12.0.0.0.11.dist-info/RECORD
